{
  "name":"broker",
  "nameAppend":"BlackDrivers",
  "mode":"vue",
  "routePath":"/crm/broker/blackdrivers",
  "title":"司机黑名单",
  "breadcrumb":[{
    "path":"/crm",
    "label":"CRM系统"
  }, {
    "path":"/broker",
    "label":"车主管理"
  }],
  "data":[
    {
      "name":"id",
      "key":true,
      "type":"string",
      "defaultValue":"",
      "title":"标识",
      "hideInQuery":true,
      "hideInInfo":true,
      "hideInList":true
    },{
      "name":"companyName",
      "type":"string",
      "defaultValue":"",
      "title":"公司名称",
      "hideInInfo":true
    },{
      "name":"brokerName",
      "type":"string",
      "defaultValue":"",
      "title":"车主名称",
      "hideInInfo":true
    },{
      "name":"brokerPhone",
      "type":"string",
      "defaultValue":"",
      "title":"车主手机号",
      "hideInInfo":true
    },{
      "name":"blackDate",
      "type":"string",
      "defaultValue":"",
      "title":"加入黑名单时间",
      "hideInInfo":true
    },{
      "name":"brokerType",
      "type":"string",
      "defaultValue":"",
      "title":"认证类型",
      "hideInInfo":true
    },{
      "name":"businessLicense",
      "type":"string",
      "defaultValue":"",
      "title":"公司营业执照",
      "hideInQuery":true,
      "hideInInfo":true
    },{
      "name":"socialId",
      "type":"string",
      "defaultValue":"",
      "title":"身份证号",
      "hideInQuery":true,
      "hideInInfo":true
    },{
      "name":"contactPhone",
      "type":"string",
      "defaultValue":"",
      "title":"联系电话",
      "hideInQuery":true,
      "hideInInfo":true
    },{
      "name":"reginsterTime",
      "type":"string",
      "defaultValue":"",
      "title":"注册时间",
      "hideInQuery":true,
      "hideInInfo":true
    },{
      "name":"blackDate",
      "type":"string",
      "defaultValue":"",
      "title":"加入黑名单时间",
      "hideInQuery":true,
      "hideInInfo":true
    },{
      "name":"operatorName",
      "type":"string",
      "defaultValue":"",
      "title":"操作人",
      "hideInQuery":true,
      "hideInInfo":true
    },{
      "name":"accountStatus",
      "type":"string",
      "defaultValue":"",
      "title":"账号状态",
      "hideInQuery":true,
      "hideInInfo":true
    }
  ]
}
